tiferet_monday/__init__.py
tiferet_monday/contexts/__init__.py
tiferet_monday/contexts/feature.py
tiferet_monday/contracts/__init__.py
tiferet_monday/contracts/item.py
tiferet_monday/data/__init__.py
tiferet_monday/data/column_value.py
tiferet_monday/data/doc.py
tiferet_monday/data/item.py
tiferet_monday/models/__init__.py
tiferet_monday/models/column_value.py
tiferet_monday/models/doc.py
tiferet_monday/models/item.py
tiferet_monday/proxies/__init__.py
tiferet_monday/proxies/requests/__init__.py
tiferet_monday/proxies/requests/doc.py
tiferet_monday/proxies/requests/item.py
tiferet_monday/proxies/requests/settings.py
tiferet_monday-0.1.2.dist-info/licenses/LICENSE
tiferet_monday-0.1.2.dist-info/METADATA
tiferet_monday-0.1.2.dist-info/WHEEL
tiferet_monday-0.1.2.dist-info/top_level.txt
tiferet_monday-0.1.2.dist-info/RECORD
